{
  "metadata": {
    "buildingId": "22BISHOPSGATE_EC2",
    "analysisDate": "2024-08-06T02:30:00Z",
    "reportingPeriod": "2024-01-01 to 2024-12-31",
    "esgScore": 93.6,
    "carbonIntensity": 0.89,
    "complianceStatus": "exceeds_targets"
  },
  "emissionsData": {
    "totalEmissions": {
      "current": 1430.5,
      "baseline": 1890.2,
      "reduction": 459.7,
      "reductionPercentage": 24.3,
      "unit": "tCO2e/year"
    },
    "scope1Emissions": {
      "current": 245.8,
      "baseline": 320.1,
      "reduction": 74.3,
      "reductionPercentage": 23.2,
      "sources": {
        "naturalGas": 180.2,
        "refrigerants": 45.6,
        "diesel": 20.0
      }
    },
    "scope2Emissions": {
      "current": 1184.7,
      "baseline": 1570.1,
      "reduction": 385.4,
      "reductionPercentage": 24.5,
      "sources": {
        "electricity": 1184.7
      }
    },
    "scope3Emissions": {
      "current": 0.0,
      "baseline": 0.0,
      "reduction": 0.0,
      "reductionPercentage": 0.0,
      "sources": {
        "businessTravel": 0.0,
        "waste": 0.0,
        "water": 0.0
      }
    }
  },
  "energyEfficiency": {
    "energyIntensity": {
      "current": 245.6,
      "baseline": 325.8,
      "improvement": 80.2,
      "improvementPercentage": 24.6,
      "unit": "kWh/m²/year"
    },
    "thermalEfficiency": {
      "current": 0.58,
      "baseline": 0.42,
      "improvement": 0.16,
      "improvementPercentage": 38.1
    },
    "renewableEnergy": {
      "current": 15.3,
      "target": 25.0,
      "gap": 9.7,
      "unit": "percentage"
    }
  },
  "carbonCredits": {
    "totalCredits": 459.7,
    "creditsGenerated": 459.7,
    "creditsPurchased": 0.0,
    "creditsSold": 0.0,
    "creditsRetired": 0.0,
    "creditsAvailable": 459.7,
    "marketValue": 13791.0,
    "currency": "GBP"
  },
  "esgMetrics": {
    "environmentalScore": 94.2,
    "socialScore": 91.8,
    "governanceScore": 94.8,
    "overallScore": 93.6,
    "rating": "AA",
    "peerComparison": "top_10_percent"
  },
  "complianceTargets": {
    "netZeroTarget": "2035",
    "interimTargets": {
      "2025": 1200,
      "2030": 800,
      "2035": 0
    },
    "currentProgress": "ahead_of_schedule",
    "riskLevel": "low"
  },
  "realTimeMonitoring": {
    "currentEmissions": 0.39,
    "dailyAverage": 3.92,
    "monthlyTotal": 119.2,
    "yearToDate": 1430.5,
    "lastUpdated": "2024-08-06T02:30:00Z",
    "trend": "decreasing"
  },
  "carbonOffsetProjects": [
    {
      "id": "offset_001",
      "name": "Scottish Highland Reforestation",
      "type": "afforestation",
      "credits": 150.0,
      "certification": "Gold Standard",
      "verification": "verified",
      "impact": "1500 trees planted, 45 hectares restored"
    },
    {
      "id": "offset_002",
      "name": "Kenya Solar Cookstoves",
      "type": "renewable_energy",
      "credits": 200.0,
      "certification": "Verified Carbon Standard",
      "verification": "verified",
      "impact": "5000 households, 2000 tCO2e avoided annually"
    },
    {
      "id": "offset_003",
      "name": "Brazilian Rainforest Protection",
      "type": "forest_conservation",
      "credits": 109.7,
      "certification": "REDD+",
      "verification": "verified",
      "impact": "1000 hectares protected, biodiversity preserved"
    }
  ],
  "investmentMetrics": {
    "carbonPrice": 30.0,
    "carbonRisk": "low",
    "transitionRisk": "medium",
    "physicalRisk": "low",
    "carbonBeta": 0.15,
    "carbonAlpha": 0.08
  }
} 